squint/__init__.py
squint/_preview.py
squint/_utils.py
squint/query.py
squint/result.py
squint/select.py
squint/_compatibility/__init__.py
squint/_compatibility/abc.py
squint/_compatibility/builtins.py
squint/_compatibility/contextlib.py
squint/_compatibility/decimal.py
squint/_compatibility/functools.py
squint/_compatibility/itertools.py
squint/_compatibility/collections/__init__.py
squint/_compatibility/collections/abc.py
squint/_vendor/__init__.py
squint/_vendor/load_csv.py
squint/_vendor/predicate.py
squint/_vendor/temptable.py
squint-0.1.0.dist-info/AUTHORS
squint-0.1.0.dist-info/LICENSE
squint-0.1.0.dist-info/METADATA
squint-0.1.0.dist-info/WHEEL
squint-0.1.0.dist-info/top_level.txt
squint-0.1.0.dist-info/RECORD
